gasprice/__init__.py
gasprice/api.py
gasprice/api_direct.py
gasprice/exceptions.py
gasprice/shared.py
gasprice/utils.py
gaspriceio-1.0.0.dist-info/LICENSE
gaspriceio-1.0.0.dist-info/METADATA
gaspriceio-1.0.0.dist-info/WHEEL
gaspriceio-1.0.0.dist-info/top_level.txt
gaspriceio-1.0.0.dist-info/RECORD
