Metadata-Version: 2.1
Name: gaspriceio
Version: 1.0.0
Summary: 🐍 Pythonic wrapper for GasPrice.io API
Home-page: https://github.com/nekusu/py-gaspriceio
Author: nekusu
Author-email: nekusu.dev@gmail.com
License: MIT
Platform: UNKNOWN
Classifier: Programming Language :: Python :: 3
Classifier: License :: OSI Approved :: MIT License
Classifier: Operating System :: OS Independent
Requires-Python: >=3.6
Requires-Dist: requests
Requires-Dist: websocket-client
